.coveragerc
.isort.cfg
CHANGES.rst
MANIFEST.in
Makefile
README.rst
buildout.cfg
ci.cfg
requirements.txt
setup.py
docs/LICENSE.GPL
docs/LICENSE.rst
src/Products/__init__.py
src/Products.CPUtils.egg-info/PKG-INFO
src/Products.CPUtils.egg-info/SOURCES.txt
src/Products.CPUtils.egg-info/dependency_links.txt
src/Products.CPUtils.egg-info/entry_points.txt
src/Products.CPUtils.egg-info/namespace_packages.txt
src/Products.CPUtils.egg-info/not-zip-safe
src/Products.CPUtils.egg-info/requires.txt
src/Products.CPUtils.egg-info/top_level.txt
src/Products/CPUtils/QITool.txt
src/Products/CPUtils/__init__.py
src/Products/CPUtils/config.py
src/Products/CPUtils/configure.zcml
src/Products/CPUtils/fckpatch.py
src/Products/CPUtils/hiddenProductsList.py
src/Products/CPUtils/plone3.zcml
src/Products/CPUtils/profiles.zcml
src/Products/CPUtils/readme.txt
src/Products/CPUtils/refresh.txt
src/Products/CPUtils/setuphandlers.py
src/Products/CPUtils/utils.py
src/Products/CPUtils/version.txt
src/Products/CPUtils/Extensions/__init__.py
src/Products/CPUtils/Extensions/ploneboard_wf_scripts.py
src/Products/CPUtils/Extensions/utils.py
src/Products/CPUtils/data/robots.txt
src/Products/CPUtils/locales/cputils.pot
src/Products/CPUtils/locales/fr/LC_MESSAGES/cputils.po
src/Products/CPUtils/model/CPUtils.zargo
src/Products/CPUtils/model/archgenxml.log
src/Products/CPUtils/model/generate.conf
src/Products/CPUtils/model/generate.sh
src/Products/CPUtils/profiles/default/cputils_default.txt
src/Products/CPUtils/profiles/default/import_steps.xml
src/Products/CPUtils/profiles/default/metadata.xml
src/Products/CPUtils/profiles/default/skins.xml
src/Products/CPUtils/profiles/robots/cputils_robots.txt
src/Products/CPUtils/profiles/robots/import_steps.xml
src/Products/CPUtils/scripts/INSTANCES.txt
src/Products/CPUtils/scripts/__init__.py
src/Products/CPUtils/scripts/checkInstances.py
src/Products/CPUtils/scripts/checkInstances.sh
src/Products/CPUtils/scripts/checkPOSKeyErrors.py
src/Products/CPUtils/scripts/checkPOSKeyErrors.sh
src/Products/CPUtils/scripts/pack_backup_db.py
src/Products/CPUtils/scripts/pack_backup_db.sh
src/Products/CPUtils/scripts/pack_db.py
src/Products/CPUtils/scripts/pack_db.sh
src/Products/CPUtils/scripts/pack_zeo.py
src/Products/CPUtils/scripts/pack_zeo.sh
src/Products/CPUtils/scripts/restore_db.py
src/Products/CPUtils/scripts/restore_db.sh
