Metadata-Version: 2.1
Name: Products.CPUtils
Version: 1.26
Summary: Some plone utilities as external methods, monkey patches, etc.
Home-page: http://pypi.python.org/pypi/Products.CPUtils
Author: Stephan Geulette
Author-email: s.geulette@imio.be
License: GPL
Keywords: plone imio utils
Platform: UNKNOWN
Classifier: Development Status :: 6 - Mature
Classifier: Environment :: Web Environment
Classifier: Framework :: Plone
Classifier: Framework :: Plone :: 4.3
Classifier: License :: OSI Approved :: GNU General Public License (GPL)
Classifier: Programming Language :: Python
Classifier: Programming Language :: Python :: 2.7
Provides-Extra: test
